mail_configuration/__init__.py
mail_configuration/admin.py
mail_configuration/apps.py
mail_configuration/constants.py
mail_configuration/models.py
mail_configuration/serializers.py
mail_configuration/tests.py
mail_configuration/utils.py
mail_configuration/views.py
mail_configuration/migrations/0001_initial.py
mail_configuration/migrations/__init__.py
mail_configuration-1.0.1.dist-info/LICENSE
mail_configuration-1.0.1.dist-info/METADATA
mail_configuration-1.0.1.dist-info/WHEEL
mail_configuration-1.0.1.dist-info/entry_points.txt
mail_configuration-1.0.1.dist-info/top_level.txt
mail_configuration-1.0.1.dist-info/RECORD
