Metadata-Version: 2.1
Name: mail-configuration
Version: 1.0.1
Summary: A Django app for configuring mail
Home-page: https://github.com/JasirMJ/solutionizeit_mail_engine
Author: jasirmj
Author-email: jasirmj@gmail.com
Maintainer: jasirmj
Maintainer-email: jasirmj@gmail.com
License: MIT
Platform: UNKNOWN
Classifier: Framework :: Django
Classifier: Operating System :: OS Independent
Classifier: Environment :: Web Environment
Classifier: Intended Audience :: Developers
Classifier: License :: OSI Approved :: MIT License
Classifier: Operating System :: OS Independent
Classifier: Programming Language :: Python :: 3
Classifier: Programming Language :: Python :: 3.7
Classifier: Programming Language :: Python :: 3.8
Classifier: Topic :: Software Development :: Libraries :: Python Modules
License-File: LICENSE
Requires-Dist: django>=3.0
Provides-Extra: dev
Requires-Dist: black; extra == "dev"
Requires-Dist: flake8; extra == "dev"
